django_admin_commander/__init__.py
django_admin_commander/admin.py
django_admin_commander/apps.py
django_admin_commander/checks.py
django_admin_commander/consts.py
django_admin_commander/exceptions.py
django_admin_commander/forms.py
django_admin_commander/models.py
django_admin_commander/py.typed
django_admin_commander/tests.py
django_admin_commander/utils.py
django_admin_commander/views.py
django_admin_commander/migrations/0001_initial.py
django_admin_commander/migrations/__init__.py
django_admin_commander/templates/django_admin_commands/admin/commands_history.html
django_admin_commander/templates/django_admin_commands/admin/run_command.html
django_admin_commander-0.4.0.dist-info/METADATA
django_admin_commander-0.4.0.dist-info/WHEEL
django_admin_commander-0.4.0.dist-info/licenses/LICENSE
django_admin_commander-0.4.0.dist-info/RECORD
