Metadata-Version: 2.4
Name: django-admin-commander
Version: 0.4.0
Summary: A Django app to run management commands from the admin panel
Project-URL: Home, https://github.com/Lcrs123/django-admin-commander
Author: Lucas Camillo
License-File: LICENSE
Requires-Python: >=3.11
Requires-Dist: django>=4.2
